kinlin/__init__.py
kinlin-0.0.1.dist-info/LICENSE.md
kinlin-0.0.1.dist-info/METADATA
kinlin-0.0.1.dist-info/WHEEL
kinlin-0.0.1.dist-info/top_level.txt
kinlin-0.0.1.dist-info/RECORD
