Metadata-Version: 2.1
Name: kinlin
Version: 0.0.1
Summary: WIP: PyTorch based framework
Home-page: https://github.com/the-lay/kinlin
Author: the-lay
Author-email: ilja@gubins.lv
License: MIT
Platform: UNKNOWN
Classifier: Development Status :: 2 - Pre-Alpha
Classifier: Intended Audience :: Developers
Classifier: Intended Audience :: Science/Research
Classifier: Topic :: Scientific/Engineering :: Artificial Intelligence
Classifier: Topic :: Software Development :: Libraries :: Python Modules
Classifier: License :: OSI Approved :: MIT License
Classifier: Programming Language :: Python :: 3 :: Only
Requires-Dist: pytorch
Requires-Dist: mrcfile
Requires-Dist: numpy
